{"nodes": [{"id": "services_cloudsync_ts", "label": "cloudSync.ts", "file_type": "code", "source_file": "services\\cloudSync.ts", "source_location": "L1"}, {"id": "cloudsync_syncupserthabit", "label": "syncUpsertHabit()", "file_type": "code", "source_file": "services\\cloudSync.ts", "source_location": "L11"}, {"id": "cloudsync_syncdeletedhabit", "label": "syncDeletedHabit()", "file_type": "code", "source_file": "services\\cloudSync.ts", "source_location": "L14"}, {"id": "cloudsync_syncupserthabitlog", "label": "syncUpsertHabitLog()", "file_type": "code", "source_file": "services\\cloudSync.ts", "source_location": "L19"}, {"id": "cloudsync_syncdeletedhabitlog", "label": "syncDeletedHabitLog()", "file_type": "code", "source_file": "services\\cloudSync.ts", "source_location": "L22"}, {"id": "cloudsync_syncupserttasklist", "label": "syncUpsertTaskList()", "file_type": "code", "source_file": "services\\cloudSync.ts", "source_location": "L31"}, {"id": "cloudsync_syncdeletedtasklist", "label": "syncDeletedTaskList()", "file_type": "code", "source_file": "services\\cloudSync.ts", "source_location": "L34"}, {"id": "cloudsync_syncupserttask", "label": "syncUpsertTask()", "file_type": "code", "source_file": "services\\cloudSync.ts", "source_location": "L39"}, {"id": "cloudsync_syncdeletedtask", "label": "syncDeletedTask()", "file_type": "code", "source_file": "services\\cloudSync.ts", "source_location": "L42"}, {"id": "cloudsync_syncupsertsettings", "label": "syncUpsertSettings()", "file_type": "code", "source_file": "services\\cloudSync.ts", "source_location": "L47"}], "edges": [{"source": "services_cloudsync_ts", "target": "types", "relation": "imports_from", "confidence": "EXTRACTED", "source_file": "services\\cloudSync.ts", "source_location": "L1", "weight": 1.0}, {"source": "services_cloudsync_ts", "target": "expo_web_browser", "relation": "imports_from", "confidence": "EXTRACTED", "source_file": "services\\cloudSync.ts", "source_location": "L2", "weight": 1.0}, {"source": "services_cloudsync_ts", "target": "services_convex", "relation": "imports_from", "confidence": "EXTRACTED", "source_file": "services\\cloudSync.ts", "source_location": "L3", "weight": 1.0}, {"source": "services_cloudsync_ts", "target": "services_convexfunctions", "relation": "imports_from", "confidence": "EXTRACTED", "source_file": "services\\cloudSync.ts", "source_location": "L4", "weight": 1.0}, {"source": "services_cloudsync_ts", "target": "cloudsync_syncupserthabit", "relation": "contains", "confidence": "EXTRACTED", "source_file": "services\\cloudSync.ts", "source_location": "L11", "weight": 1.0}, {"source": "services_cloudsync_ts", "target": "cloudsync_syncdeletedhabit", "relation": "contains", "confidence": "EXTRACTED", "source_file": "services\\cloudSync.ts", "source_location": "L14", "weight": 1.0}, {"source": "services_cloudsync_ts", "target": "cloudsync_syncupserthabitlog", "relation": "contains", "confidence": "EXTRACTED", "source_file": "services\\cloudSync.ts", "source_location": "L19", "weight": 1.0}, {"source": "services_cloudsync_ts", "target": "cloudsync_syncdeletedhabitlog", "relation": "contains", "confidence": "EXTRACTED", "source_file": "services\\cloudSync.ts", "source_location": "L22", "weight": 1.0}, {"source": "services_cloudsync_ts", "target": "cloudsync_syncupserttasklist", "relation": "contains", "confidence": "EXTRACTED", "source_file": "services\\cloudSync.ts", "source_location": "L31", "weight": 1.0}, {"source": "services_cloudsync_ts", "target": "cloudsync_syncdeletedtasklist", "relation": "contains", "confidence": "EXTRACTED", "source_file": "services\\cloudSync.ts", "source_location": "L34", "weight": 1.0}, {"source": "services_cloudsync_ts", "target": "cloudsync_syncupserttask", "relation": "contains", "confidence": "EXTRACTED", "source_file": "services\\cloudSync.ts", "source_location": "L39", "weight": 1.0}, {"source": "services_cloudsync_ts", "target": "cloudsync_syncdeletedtask", "relation": "contains", "confidence": "EXTRACTED", "source_file": "services\\cloudSync.ts", "source_location": "L42", "weight": 1.0}, {"source": "services_cloudsync_ts", "target": "cloudsync_syncupsertsettings", "relation": "contains", "confidence": "EXTRACTED", "source_file": "services\\cloudSync.ts", "source_location": "L47", "weight": 1.0}]}